Metadata-Version: 1.1
Name: partial.py
Version: 0.1.2
Summary: Functional Python Library
Home-page: https://github.com/marpple/partial.py
Author: Marpple
Author-email: dev@marpple.com
License: MIT
Platform: UNKNOWN
Classifier: Development Status :: 1 - Planning
Classifier: Environment :: Web Environment
Classifier: License :: OSI Approved :: MIT License
Classifier: Programming Language :: Python :: 3.5
Classifier: Programming Language :: Python :: 3.6
